{
	"aberdeen_city_council": {
		"count": 45,
		"data": [
			{ "type": "html", "url": "https://www.aberdeencity.gov.uk/services/people-and-communities/warm-spaces" }
		],
		"geocount": 45,
		"id": "aberdeen_city_council",
		"map": { "type": "googlemap", "url": "https://www.aberdeencity.gov.uk/services/people-and-communities/warm-spaces" },
		"register": { "url": "mailto:warmspace@aberdeencity.gov.uk" },
		"title": "Aberdeen City Council",
		"url": "https://www.aberdeencity.gov.uk/services/people-and-communities/warm-spaces"
	},
	"angus_council": {
		"id": "angus_council",
		"map": { "type": "locationCentre", "url": "https://www.angus.gov.uk/community_spaces?page_id=1626#item-details" },
		"notes": "locationCentre is not queryable",
		"title": "Angus Council",
		"url": "https://www.angus.gov.uk/community_spaces"
	},
	"ards_and_north_down_council": {
		"id": "ards_and_north_down_council",
		"notes": "Provided as a PDF",
		"register": { "url": "https://engage.ardsandnorthdown.gov.uk/community-planning/warmwelcomespace/" },
		"title": "Ards and North Down Council",
		"url": "https://www.ardsandnorthdown.gov.uk/resident/community/warm-welcome-here-campaign"
	},
	"argyll_and_bute_third_sector_interface": {
		"id": "argyll_and_bute_third_sector_interface",
		"title": "Argyll and Bute Third Sector Interface",
		"url": "https://www.argylltsi.org/warmspaces.html"
	},
	"armagh_city__bandridge_and_craigavon_council": {
		"id": "armagh_city__bandridge_and_craigavon_council",
		"title": "Armagh City, Bandridge and Craigavon Council",
		"url": "https://www.armaghbanbridgecraigavon.gov.uk/costofliving/#warmspaces"
	},
	"barnet_council": {
		"count": 18,
		"data": [
			{ "type": "html", "url": "https://www.barnet.gov.uk/directories/warm-spaces" }
		],
		"geocount": 18,
		"id": "barnet_council",
		"map": { "type": "leaflet", "url": "https://www.barnet.gov.uk/directories/warm-spaces" },
		"register": { "url": "https://www.barnet.gov.uk/benefits-grants-and-financial-advice/cost-living-support/warm-spaces-barnet/provide-warm-space" },
		"title": "Barnet Council",
		"url": "https://www.barnet.gov.uk/directories/warm-spaces"
	},
	"barnsley_council": {
		"id": "barnsley_council",
		"notes": "Refers people to Warm Welcome UK",
		"title": "Barnsley Council",
		"url": "https://www.barnsley.gov.uk/news/welcoming-spaces-in-barnsley-organisations-encouraged-to-register-their-offer/"
	},
	"basildon_council": {
		"id": "basildon_council",
		"notes": "Not enough structure to parse",
		"title": "Basildon Council",
		"url": "https://basildon.gov.uk/article/9481/Activities-and-places-to-go"
	},
	"bath_and_north_east_somerset_council": {
		"count": "0",
		"data": [
			{ "type": "html", "url": "https://livewell.bathnes.gov.uk/warm-places-map" }
		],
		"geocount": "0",
		"id": "bath_and_north_east_somerset_council",
		"map": { "type": "leaflet", "url": "https://livewell.bathnes.gov.uk/warm-places-map" },
		"title": "Bath and North East Somerset Council",
		"url": "https://livewell.bathnes.gov.uk/warm-places-list"
	},
	"bedford_council": {
		"count": 29,
		"data": [
			{ "type": "html", "url": "https://www.bedford.gov.uk/benefits-and-support/warm-spaces" }
		],
		"geocount": 29,
		"id": "bedford_council",
		"title": "Bedford Council",
		"url": "https://www.bedford.gov.uk/benefits-and-support/warm-spaces"
	},
	"belfast_council": {
		"id": "belfast_council",
		"notes": "Not enough location information to parse",
		"title": "Belfast Council",
		"url": "https://www.belfastcity.gov.uk/Community/Warm-Spaces-Warm-Welcome"
	},
	"bexley_council": {
		"count": "0",
		"data": [
			{ "type": "html", "url": "https://www.bexley.gov.uk/news/warm-welcome-across-bexley" }
		],
		"geocount": "0",
		"id": "bexley_council",
		"register": { "url": "https://forms.office.com/r/x39WnQanNv" },
		"title": "Bexley Council",
		"url": "https://www.bexley.gov.uk/news/warm-welcome-across-bexley"
	},
	"birmingham_council": {
		"count": "0",
		"data": [
			{ "robots": "", "type": "jadu", "url": "https://www.birmingham.gov.uk/directory/73/warm_welcome_spaces_in_birmingham" }
		],
		"geocount": "0",
		"id": "birmingham_council",
		"notes": "Birmingham's webserver blocks automated access",
		"register": { "url": "https://www.birmingham.gov.uk/info/50274/cost_of_living_support/2637/birmingham_warm_welcome_spaces/2" },
		"title": "Birmingham Council",
		"url": "https://www.birmingham.gov.uk/info/50274/cost_of_living_support/2637/birmingham_warm_welcome_spaces"
	},
	"bolton_at_home": {
		"count": 30,
		"data": [
			{ "type": "html", "url": "https://www.boltonathome.org.uk/warm-spaces/" }
		],
		"geocount": 27,
		"id": "bolton_at_home",
		"title": "Bolton at Home",
		"url": "https://www.boltonathome.org.uk/warm-spaces/"
	},
	"boston_borough_council": {
		"id": "boston_borough_council",
		"title": "Boston Borough Council",
		"url": "https://www.boston.gov.uk/article/22192/Warm-Spaces"
	},
	"bournemouth__christchurch_and_poole": {
		"id": "bournemouth__christchurch_and_poole",
		"register": { "url": "https://www.bcpcouncil.gov.uk/Communities/Cost-of-living-help/Warm-welcome-spaces/How-you-can-help-with-warm-welcome-spaces.aspx" },
		"title": "Bournemouth, Christchurch and Poole",
		"url": "https://www.bcpcouncil.gov.uk/Communities/Cost-of-living-help/Warm-welcome-spaces/Find-a-warm-welcome-space.aspx"
	},
	"bracknell_forest_council": {
		"id": "bracknell_forest_council",
		"title": "Bracknell Forest Council",
		"url": "https://www.bracknell-forest.gov.uk/cost-living-support/community-winter-hubs"
	},
	"bradford_council": {
		"count": 160,
		"data": [
			{ "type": "html", "url": "https://costoflivingbradford.co.uk/warm-spaces-directory/" }
		],
		"geocount": 160,
		"id": "bradford_council",
		"map": { "type": "googlemap", "url": "https://costoflivingbradford.co.uk/warm-spaces-directory/" },
		"title": "Bradford Council",
		"url": "https://costoflivingbradford.co.uk/warm-spaces/"
	},
	"brent": {
		"id": "brent",
		"notes": "Refers people to Warm Welcome",
		"title": "Brent",
		"url": "https://www.brent.gov.uk/cost-of-living-help-and-advice"
	},
	"brighton___hove_council": {
		"count": 39,
		"data": [
			{ "type": "html", "url": "https://www.brighton-hove.gov.uk/cost-living-support/warm-welcome-indoor-activities-and-warm-places-go-winter" }
		],
		"geocount": 39,
		"id": "brighton___hove_council",
		"map": { "type": "leaflet", "url": "https://www.brighton-hove.gov.uk/cost-living-support/warm-welcome-indoor-activities-and-warm-places-go-winter" },
		"title": "Brighton & Hove Council",
		"url": "https://www.brighton-hove.gov.uk/cost-living-support/warm-welcome-indoor-activities-and-warm-places-go-winter"
	},
	"bristol_council": {
		"count": 80,
		"data": [
			{ "keys": { "address": "ADDRESS", "contact": "CONTACT", "hours": "TIMETABLE", "title": "NAME", "url": "WEB" }, "type": "arcgis", "url": "https://services2.arcgis.com/a4vR8lmmksFixzmB/arcgis/rest/services/Welcoming_spaces_view/FeatureServer/0/query?f=geojson&where=WS_OPEN%20%3D%20%27Yes%27&returnGeometry=true&spatialRel=esriSpatialRelIntersects&outFields=*&maxRecordCountFactor=5&outSR=4326&resultOffset=0&resultRecordCount=5000&cacheHint=true&quantizationParameters=%7B%22mode%22%3A%22view%22%2C%22originPosition%22%3A%22upperLeft%22%2C%22tolerance%22%3A1.0583333333333336%2C%22extent%22%3A%7B%22xmin%22%3A351616%2C%22ymin%22%3A167463%2C%22xmax%22%3A364223.8694719222%2C%22ymax%22%3A179202%2C%22spatialReference%22%3A%7B%22wkid%22%3A27700%2C%22latestWkid%22%3A27700%7D%7D%7D" }
		],
		"geocount": 80,
		"id": "bristol_council",
		"map": { "type": "arcgis", "url": "https://bcc.maps.arcgis.com/apps/webappviewer/index.html?id=4c5e933568424768bd871cea2003da34" },
		"title": "Bristol Council",
		"url": "https://www.bristol.gov.uk/residents/people-and-communities/welcoming-spaces/find-a-welcoming-space"
	},
	"bromley_well": {
		"count": 50,
		"data": [
			{ "keys": { "address": "{{ street }}, {{ Postcode }}", "contact": "Tel: {{ Phone }}; Email: {{ Email }}", "description": "Notes", "hours": "Notes", "title": "name", "url": "Web" }, "type": "googlemap", "url": "https://www.google.com/maps/d/embed?mid=1eYVcD610uCwHd9GsPmiZ3EE_KR3u7iM&hl=en&ehbc=2E312F&ll=51.374733987541894%2C0.020678999999996783&z=11" }
		],
		"geocount": 50,
		"id": "bromley_well",
		"map": { "type": "googlemap", "url": "https://www.google.com/maps/d/embed?mid=1eYVcD610uCwHd9GsPmiZ3EE_KR3u7iM&hl=en&ehbc=2E312F&ll=51.374733987541894%2C0.020678999999996783&z=11" },
		"title": "Bromley Well",
		"url": "https://www.bromleywell.org.uk/news/find-your-nearest-warm-centre/"
	},
	"buckinghamshire_council": {
		"id": "buckinghamshire_council",
		"register": { "url": "https://www.buckinghamshire.gov.uk/cost-of-living/community-toolkit-register-as-a-welcoming-space/how-to-register-your-welcoming-space/" },
		"title": "Buckinghamshire Council",
		"url": "https://www.buckinghamshire.gov.uk/cost-of-living/find-a-place-to-keep-warm-welcoming-spaces/"
	},
	"cambridge_council": {
		"count": 19,
		"data": [
			{ "type": "html", "url": "https://www.cambridge.gov.uk/warm-and-welcoming-spaces" }
		],
		"geocount": 11,
		"id": "cambridge_council",
		"title": "Cambridge Council",
		"url": "https://www.cambridge.gov.uk/warm-and-welcoming-spaces"
	},
	"camden_council": {
		"count": 1,
		"data": [
			{ "type": "html", "url": "https://www.camden.gov.uk/warm-spaces-in-camden" }
		],
		"geocount": "0",
		"id": "camden_council",
		"map": { "type": "arcgis", "url": "https://ssa.camden.gov.uk/connect/analyst/mobile/#/main?mapcfg=%2FMapProjects%2FWarmSpacesMap" },
		"register": { "url": "https://forms.office.com/pages/responsepage.aspx?id=NEqPXtsrVEi7QrTQx9AkbMIlX2RFq2ZPjyjaXoTGKaNUOE9PV0ZCUkNNUkNYUElNQlAyVEVTMkFGVS4u" },
		"title": "Camden Council",
		"url": "https://www.camden.gov.uk/warm-spaces-in-camden"
	},
	"carefree_cornwall": {
		"count": 49,
		"data": [
			{ "keys": { "address": "Address", "description": "Whats on offer", "hours": "Days / times available", "title": "name" }, "type": "googlemap", "url": "https://www.google.com/maps/d/embed?mid=1Zb6kSYdWEp1eX8dAoch_ezTuaEzYSQ4&ehbc=2E312F" }
		],
		"geocount": 45,
		"id": "carefree_cornwall",
		"map": { "type": "googlemap", "url": "https://www.google.com/maps/d/embed?mid=1Zb6kSYdWEp1eX8dAoch_ezTuaEzYSQ4&ehbc=2E312F" },
		"title": "Carefree Cornwall",
		"url": "http://carefreecornwall.org.uk/warm-banks-in-cornwall/"
	},
	"central_bedfordshire_council": {
		"count": "0",
		"data": [
			{ "type": "portal", "url": "https://www.centralbedfordshire.gov.uk/directory/110/a_to_z" }
		],
		"geocount": "0",
		"id": "central_bedfordshire_council",
		"title": "Central Bedfordshire Council",
		"url": "https://www.centralbedfordshire.gov.uk/info/165/support_with_the_cost_of_living/1264/warm_spaces"
	},
	"cheshire_west_and_chester_council": {
		"id": "cheshire_west_and_chester_council",
		"notes": "Refers people to Warm Welcome",
		"title": "Cheshire West and Chester Council",
		"url": "https://www.cheshirewestandchester.gov.uk/residents/housing-benefit-council-tax/cost-of-living-support/warm-welcoming-spaces"
	},
	"chesterfield_council": {
		"count": 26,
		"data": [
			{ "keys": { "hours": "description", "title": "name" }, "type": "googlemap", "url": "https://www.google.com/maps/d/u/0/embed?mid=1KkfzxdLSd2nHiPsI6_xkcU7EBOjFmb0&ll=53.24318292347753%2C-1.4144078500000035&z=13" }
		],
		"geocount": 26,
		"id": "chesterfield_council",
		"map": { "type": "googlemap", "url": "https://www.google.com/maps/d/u/0/viewer?mid=1KkfzxdLSd2nHiPsI6_xkcU7EBOjFmb0&ll=53.24318292347753%2C-1.4144078500000035&z=13" },
		"title": "Chesterfield Council",
		"url": "https://www.chesterfield.gov.uk/home/latest-news/find-a-warm-space-to-visit-in-chesterfield.aspx"
	},
	"chichester_deanery": {
		"id": "chichester_deanery",
		"notes": "Not enough location information",
		"title": "Chichester Deanery",
		"url": "https://www.chichesterdeanery.org/warmspaces.htm"
	},
	"city_of_london": {
		"id": "city_of_london",
		"notes": "Refers to Warm Welcome UK",
		"title": "City of London",
		"url": "https://www.cityoflondon.gov.uk/services/getting-help-with-the-cost-of-living/find-a-warm-welcome-space"
	},
	"coventry_council": {
		"count": 50,
		"data": [
			{ "type": "html", "url": "https://www.coventry.gov.uk/directory/search?directoryID=115&showInMap=1&keywords=coventry&postcode=&search=Search" }
		],
		"geocount": 50,
		"id": "coventry_council",
		"map": { "type": "googlemap", "url": "https://www.coventry.gov.uk/directory/search?directoryID=115&showInMap=1&keywords=coventry&postcode=&search=Search" },
		"title": "Coventry Council",
		"url": "https://www.coventry.gov.uk/cost-living-wellbeing-support"
	},
	"croydon_simply_connect": {
		"count": 17,
		"data": [
			{ "type": "html", "url": "https://croydon.simplyconnect.uk/api/services/directory?keyword=warm-space&post_code=Croydon&distance=&region=&category=&verified=&page=1&limit=200&sort=" }
		],
		"geocount": 17,
		"id": "croydon_simply_connect",
		"title": "Croydon Simply Connect",
		"url": "https://croydon.simplyconnect.uk/activities?keyword=warm-space&post_code=Croydon&page=1&limit=20&sort="
	},
	"derbyshire_council": {
		"id": "derbyshire_council",
		"notes": "Too unstructured to parse",
		"title": "Derbyshire Council",
		"url": "https://www.derbyshire.gov.uk/social-health/health-and-wellbeing/your-health/keeping-warm-in-winter/warm-spaces/warm-spaces.aspx"
	},
	"derbyshire_dales_council": {
		"id": "derbyshire_dales_council",
		"notes": "Too unstructured to parse",
		"title": "Derbyshire Dales Council",
		"url": "https://www.derbyshiredales.gov.uk/housing-a-council-tax/benefits/warms-spaces"
	},
	"durham_county_council": {
		"count": 100,
		"data": [
			{ "type": "html", "url": "https://www.durhamlocate.org.uk/Search?CategoryId=152&SM=ServiceSearch&UDG=True&SME=True" }
		],
		"geocount": 99,
		"id": "durham_county_council",
		"map": { "type": "googlemap", "url": "https://www.durhamlocate.org.uk/Search?CategoryId=152&SM=ServiceSearch&UDG=True&SME=True" },
		"register": { "url": "https://www.durham.gov.uk/article/28229/Warm-Spaces-Network" },
		"title": "Durham County Council",
		"url": "https://www.durhamlocate.org.uk/Search?CategoryId=152&SM=ServiceSearch&UDG=True&SME=True"
	},
	"ealing_council": {
		"id": "ealing_council",
		"title": "Ealing Council",
		"url": "https://www.ealing.gov.uk/info/201320/cost_of_living_support_and_advice/3116/warm_spacesSaving"
	},
	"east_ayrshire_council": {
		"id": "east_ayrshire_council",
		"title": "East Ayrshire Council",
		"url": "https://www.east-ayrshire.gov.uk/Community/cost-of-living/community/warm-spaces.aspx"
	},
	"edinburgh_council": {
		"count": 59,
		"data": [
			{ "keys": { "address": "Address", "contact": "Tel: {{ phone }}; Email: {{ mail }}", "description": "Facilities", "hours": "opening_ho", "title": "{{ Library }}{{ Organisati }}", "url": "Web_URL" }, "type": "arcgis", "url": "https://services-eu1.arcgis.com/FgpikkYuSUOuITxp/arcgis/rest/services/CEC_Resilience_Centres/FeatureServer/3/query?f=geojson&cacheHint=true&maxRecordCountFactor=4&resultOffset=0&resultRecordCount=8000&where=1%3D1&orderByFields=FID&outFields=Address%2CEvents%2CFacilities%2CImage_URL%2CLibrary%2CWeb_URL%2CWebsite%2Cmail%2Copening_ho%2Cphone%2Cpostcode%2CFID&outSR=4326&spatialRel=esriSpatialRelIntersects" },
			{ "keys": { "address": "Address", "contact": "Tel: {{ phone }}; Email: {{ mail }}", "description": "Facilities", "hours": "opening_ho", "title": "{{ Library }}{{ Organisati }}", "url": "Web_URL" }, "type": "arcgis", "url": "https://services-eu1.arcgis.com/FgpikkYuSUOuITxp/arcgis/rest/services/CEC_Resilience_Centres/FeatureServer/2/query?f=geojson&cacheHint=true&maxRecordCountFactor=4&resultOffset=0&resultRecordCount=8000&where=1%3D1&orderByFields=FID&outFields=Address%2CEvents%2CFacilities%2COrganisati%2CWebsite%2Cmail%2Copening_ho%2Cphone%2Cpostcode%2CFID&outSR=4326&spatialRel=esriSpatialRelIntersects" },
			{ "keys": { "address": "Address", "contact": "Tel: {{ phone }}; Email: {{ mail }}", "description": "Facilities", "hours": "opening_ho", "title": "{{ Library }}{{ Organisati }}", "url": "Web_URL" }, "type": "arcgis", "url": "https://services-eu1.arcgis.com/FgpikkYuSUOuITxp/arcgis/rest/services/CEC_Resilience_Centres/FeatureServer/1/query?f=geojson&cacheHint=true&maxRecordCountFactor=4&resultOffset=0&resultRecordCount=8000&where=1%3D1&orderByFields=FID&outFields=FID%2COrganisati&outSR=4326&spatialRel=esriSpatialRelIntersects" },
			{ "keys": { "address": "Address", "contact": "Tel: {{ phone }}; Email: {{ mail }}", "description": "Facilities", "hours": "opening_ho", "title": "{{ Library }}{{ Organisati }}", "url": "Web_URL" }, "type": "arcgis", "url": "https://services-eu1.arcgis.com/FgpikkYuSUOuITxp/arcgis/rest/services/CEC_Resilience_Centres/FeatureServer/0/query?f=geojson&cacheHint=true&maxRecordCountFactor=4&resultOffset=0&resultRecordCount=8000&where=1%3D1&orderByFields=FID&outFields=Address%2CEvents%2CFacilities%2COrganisati%2CWebsite%2Cmail%2Copening_ho%2Cphone%2Cpostcode%2CFID&outSR=4326&spatialRel=esriSpatialRelIntersects" }
		],
		"geocount": 59,
		"id": "edinburgh_council",
		"map": { "type": "arcgis", "url": "https://cityofedinburgh.maps.arcgis.com/apps/instant/basic/index.html?appid=b12a908ff5a240bca9c52ecb480b0c37" },
		"title": "Edinburgh Council",
		"url": "https://www.edinburgh.gov.uk/warm-welcoming-spaces"
	},
	"enfield_council": {
		"id": "enfield_council",
		"notes": "Refers people to Warm Welcome",
		"title": "Enfield Council",
		"url": "https://www.enfield.gov.uk/services/your-council/cost-of-living-support/warm-spaces"
	},
	"fylde_council": {
		"id": "fylde_council",
		"register": { "url": "mailto:edyta.paxton@fylde.gov.uk" },
		"title": "Fylde Council",
		"url": "https://fylde.gov.uk/warm-spaces-in-fylde/"
	},
	"gateshead_council": {
		"count": 30,
		"data": [
			{ "type": "html", "url": "https://www.gateshead.gov.uk/article/21258/Warm-Spaces-directory" }
		],
		"geocount": 30,
		"id": "gateshead_council",
		"map": { "type": "googlemap", "url": "https://www.gateshead.gov.uk/article/21258/Warm-Spaces-directory?view=map&q=*" },
		"title": "Gateshead Council",
		"url": "https://www.gateshead.gov.uk/article/21258/Warm-Spaces-directory"
	},
	"gedling_council": {
		"count": 31,
		"data": [
			{ "type": "html", "url": "https://www.gedling.gov.uk/resident/community/costoflivingsupport/warmspaces/" }
		],
		"geocount": 30,
		"id": "gedling_council",
		"title": "Gedling Council",
		"url": "https://www.gedling.gov.uk/resident/community/costoflivingsupport/warmspaces/"
	},
	"greenwich_council": {
		"count": 33,
		"data": [
			{ "type": "html", "url": "https://www.royalgreenwich.gov.uk/directory/106/warm_spaces_across_royal_greenwich" }
		],
		"geocount": 33,
		"id": "greenwich_council",
		"map": { "type": "googlemap", "url": "https://www.royalgreenwich.gov.uk/directory/106/warm_spaces_across_royal_greenwich" },
		"title": "Greenwich Council",
		"url": "https://www.royalgreenwich.gov.uk/info/200344/supporting_you/2412/warm_spaces_in_royal_greenwich"
	},
	"haringey_council": {
		"count": 17,
		"data": [
			{ "type": "html", "url": "https://www.haringey.gov.uk/community/haringey-warm-welcome" }
		],
		"geocount": 17,
		"id": "haringey_council",
		"title": "Haringey Council",
		"url": "https://www.haringey.gov.uk/community/haringey-warm-welcome"
	},
	"harrogate_netmakers": {
		"count": 15,
		"data": [
			{ "keys": { "hours": "description", "title": "name" }, "type": "googlemap", "url": "https://www.google.com/maps/d/u/1/embed?mid=132pQ79bvABq8HA9j_OZAI39Gb7rkXuY&ehbc=2E312F" }
		],
		"geocount": 15,
		"id": "harrogate_netmakers",
		"map": { "type": "googlemap", "url": "https://www.google.com/maps/d/u/1/embed?mid=132pQ79bvABq8HA9j_OZAI39Gb7rkXuY&ehbc=2E312F" },
		"title": "Harrogate NetMakers",
		"url": "http://netmakers.org.uk/warmwelcome/"
	},
	"havering_council": {
		"count": 19,
		"data": [
			{ "type": "html", "url": "https://www.havering.gov.uk/info/20096/community/883/warm_spaces" }
		],
		"geocount": 15,
		"id": "havering_council",
		"title": "Havering Council",
		"url": "https://www.havering.gov.uk/info/20096/community/883/warm_spaces"
	},
	"high_peak_council": {
		"count": 28,
		"data": [
			{ "type": "html", "url": "https://www.highpeak.gov.uk/CostOfLiving-WelcomingSpaces" }
		],
		"geocount": 23,
		"id": "high_peak_council",
		"title": "High Peak Council",
		"url": "https://www.highpeak.gov.uk/CostOfLiving-WelcomingSpaces"
	},
	"hounslow_council": {
		"count": 35,
		"data": [
			{ "type": "html", "url": "https://www.hounslow.gov.uk/warmspaces" }
		],
		"geocount": "0",
		"id": "hounslow_council",
		"title": "Hounslow Council",
		"url": "https://www.hounslow.gov.uk/warmspaces"
	},
	"hull_council": {
		"count": 29,
		"data": [
			{ "keys": { "address": "{{ fields->sheet1__f5 }}, {{ fields->sheet1__f6 }}, {{ fields->sheet1__f7 }}", "contact": "fields->sheet1__f9", "description": "fields->activities", "title": "fields->sheet1__f4", "url": "links->sheet1__f4" }, "type": "geojson", "url": "https://maps.hull.gov.uk/GetOWS.ashx?VERSION=1.0.0&SERVICE=WFS&REQUEST=GetFeature&TYPENAME=Warm_Spaces&MAPSOURCE=mapsources/AllMaps&OUTPUTFORMAT=GeoJSON_BBOX&FILTER=%3Cogc:Filter%20xmlns:ogc=%22http://www.opengis.net/ogc%22%3E%3Cogc:Intersects%3E%3Cogc:PropertyName%3Ewkb_geometry%3C/ogc:PropertyName%3E%3Cgml:Polygon%20xmlns:gml=%22http://www.opengis.net/gml%22%3E%3Cgml:exterior%3E%3Cgml:LinearRing%3E%3Cgml:posList%3E519000%20423000%20519000%20438000%20497000%20438000%20497000%20423000%20519000%20423000%3C/gml:posList%3E%3C/gml:LinearRing%3E%3C/gml:exterior%3E%3C/gml:Polygon%3E%3C/ogc:Intersects%3E%3C/ogc:Filter%3E&VIEWPARAMS=bbox(%22%22,%22497887,423581,517495,437666%22)" }
		],
		"geocount": 29,
		"id": "hull_council",
		"map": { "type": "iShare", "url": "https://maps.hull.gov.uk/?tab=maps&Layers=Warm_Spaces" },
		"title": "Hull Council",
		"url": "https://www.hull.gov.uk/benefits-support-and-welfare-advice/debt-and-money/cost-living"
	},
	"huntingdonshire_council": {
		"count": 40,
		"data": [
			{ "type": "html", "url": "https://www.huntingdonshire.gov.uk/people-communities/warm-spaces/warm-spaces-locations/" }
		],
		"geocount": 40,
		"id": "huntingdonshire_council",
		"map": { "type": "googlemap", "url": "https://www.huntingdonshire.gov.uk/people-communities/warm-spaces/" },
		"title": "Huntingdonshire Council",
		"url": "https://www.huntingdonshire.gov.uk/people-communities/warm-spaces/"
	},
	"islington_council": {
		"count": 40,
		"data": [
			{ "type": "html", "url": "https://www.islington.gov.uk/benefits-and-support/cost-of-living-support/warm-community-spaces" }
		],
		"geocount": 40,
		"id": "islington_council",
		"title": "Islington Council",
		"url": "https://www.islington.gov.uk/benefits-and-support/cost-of-living-support/warm-community-spaces"
	},
	"kensington_and_chelsea": {
		"count": 26,
		"data": [
			{ "keys": { "address": "Address", "contact": "Contact_Information", "hours": "Timings_and_Offers", "title": "Venue", "url": "Weblink" }, "type": "arcgis", "url": "https://utility.arcgis.com/usrsvcs/servers/599218e67dc34f369b8d941491bb565a/rest/services/RBKC/GeneralServices/MapServer/82/query?f=json&cacheHint=true&resultOffset=0&resultRecordCount=1000&where=1%3D1&orderByFields=OBJECTID&outFields=*&outSR=4326&spatialRel=esriSpatialRelIntersects" }
		],
		"geocount": 26,
		"id": "kensington_and_chelsea",
		"map": { "type": "arcgis", "url": "https://lbhf.maps.arcgis.com/apps/instant/nearby/index.html?appid=e7e3050fbb8e49b79b5743bf17b9c720&sliderDistance=400&findSource=1&find=-23824.558013193524%252C6713243.6715945285" },
		"title": "Kensington and Chelsea",
		"url": "https://www.rbkc.gov.uk/cost-living-support-hub/warm-spaces-kensington-and-chelsea"
	},
	"kingston_council": {
		"count": 31,
		"data": [
			{ "keys": { "description": "description", "hours": "description", "title": "name" }, "type": "googlemap", "url": "https://www.google.com/maps/d/u/0/embed?hl=en&ll=51.41010910537069%2C-0.2977900670410172&z=13&mid=18qlVM3JMV-aKnLig17V9mmEakLlR3Vc" }
		],
		"geocount": 31,
		"id": "kingston_council",
		"map": { "type": "googlemap", "url": "https://www.google.com/maps/d/u/0/viewer?hl=en&ll=51.41010910537069%2C-0.2977900670410172&z=13&mid=18qlVM3JMV-aKnLig17V9mmEakLlR3Vc" },
		"register": { "url": "https://docs.google.com/forms/d/e/1FAIpQLSd3W0eRlVADHwMI5Wf1eA94IsEcysZVZlbAOfCbDJNgK3FZzg/viewform?usp=sf_link" },
		"title": "Kingston Council",
		"url": "https://www.kingston.gov.uk/benefits-5/support-rising-living-costs/10"
	},
	"kirklees_council": {
		"id": "kirklees_council",
		"notes": "Mentions libraries and refers to Warm Welcome UK",
		"title": "Kirklees Council",
		"url": "https://www.kirklees.gov.uk/beta/cost-of-living/warm-spaces.aspx"
	},
	"lambeth_council": {
		"count": 20,
		"data": [
			{ "type": "html", "url": "https://beta.lambeth.gov.uk/warm-spaces" }
		],
		"geocount": 20,
		"id": "lambeth_council",
		"map": { "type": "leaflet", "url": "https://beta.lambeth.gov.uk/warm-spaces" },
		"register": { "url": "https://forms.lambeth.gov.uk/SIGNUPTOBEAWARMSPACE/launch" },
		"title": "Lambeth Council",
		"url": "https://beta.lambeth.gov.uk/warm-spaces"
	},
	"lancashire_council": {
		"id": "lancashire_council",
		"register": { "url": "https://www.lancashire.gov.uk/health-and-social-care/cost-of-living/warm-spaces/register-as-a-warm-space/" },
		"title": "Lancashire Council",
		"url": "https://www.lancashire.gov.uk/health-and-social-care/cost-of-living/warm-and-welcome-places/"
	},
	"leeds_city_council": {
		"count": 146,
		"data": [
			{ "keys": { "accessibility": "Accessibility_Comments", "address": "Address", "description": "Description", "friday": "Friday", "lat": "Latitude", "lon": "Longitude", "monday": "Monday", "saturday": "Saturday", "sunday": "Sunday", "thursday": "Thursday", "title": "Venue", "tuesday": "Tuesday", "type": "Venue_Type", "wednesday": "Wednesday" }, "type": "arcgis", "url": "https://services1.arcgis.com/brSffcdOV7o1pDVT/arcgis/rest/services/WarmSpacesNov_Public_View/FeatureServer/0/query?f=geojson&cacheHint=true&maxRecordCountFactor=4&resultOffset=0&resultRecordCount=8000&where=1%3D1&orderByFields=OBJECTID&outFields=*&outSR=4326&spatialRel=esriSpatialRelIntersects" }
		],
		"geocount": 146,
		"id": "leeds_city_council",
		"licence": "OGLv3",
		"map": { "type": "arcgis", "url": "https://experience.arcgis.com/experience/d6adbf692a7b4cfb8250b36bf8501a90/" },
		"register": { "url": "https://experience.arcgis.com/experience/2264b176caef4da292a4647c057938bf/" },
		"title": "Leeds City Council",
		"url": "https://www.leeds.gov.uk/campaign/warm-spaces"
	},
	"leicester_council": {
		"id": "leicester_council",
		"title": "Leicester Council",
		"url": "https://www.leicester.gov.uk/your-community/benefits-and-support/find-a-warm-space/"
	},
	"lewes_and_eastbourne_council": {
		"id": "lewes_and_eastbourne_council",
		"register": "https://www.lewes-eastbourne.gov.uk/community/cost-of-living-crisis/warm-spaces/application-form/",
		"title": "Lewes and Eastbourne Council",
		"url": "https://www.lewes-eastbourne.gov.uk/community/cost-of-living-crisis/warm-spaces/"
	},
	"lewisham_local": {
		"id": "lewisham_local",
		"map": { "type": "googlemap", "url": "https://www.lewishamlocal.com/places/category/lewishamwarmwelcome/" },
		"notes": "Unable to extract enough data",
		"title": "Lewisham Local",
		"url": "https://www.lewishamlocal.com/lewisham-warm-spaces/"
	},
	"litchfield_council": {
		"count": 15,
		"data": [
			{ "type": "html", "url": "https://www.lichfielddc.gov.uk/homepage/159/warm-spaces-map" }
		],
		"geocount": 15,
		"id": "litchfield_council",
		"map": { "type": "googlemap", "url": "https://www.lichfielddc.gov.uk/homepage/159/warm-spaces-map" },
		"title": "Litchfield Council",
		"url": "https://www.lichfielddc.gov.uk/homepage/159/warm-spaces-map"
	},
	"live_well_york": {
		"id": "live_well_york",
		"title": "Live Well York",
		"url": "https://www.livewellyork.co.uk/search/?searchTab=productsTab&sortOption=Rank%3Basc&pageNumber=1&pageSize=50&services.0=5bdc51f7-e332-43e1-9d1b-af0a00dd6f90&postcodeOptions.distance=1609"
	},
	"merton_council": {
		"id": "merton_council",
		"notes": "A list of libraries",
		"title": "Merton Council",
		"url": "https://libraries.merton.gov.uk/client/en_GB/merton/?rm=BRANCHES2%7C%7C%7C1%7C%7C%7C0%7C%7C%7Ctrue"
	},
	"mid_and_east_antrim_council": {
		"count": 13,
		"data": [
			{ "type": "html", "url": "https://www.midandeastantrim.gov.uk/resident/healthandwellbeing/a-safe-warm-well-come/" }
		],
		"geocount": 8,
		"id": "mid_and_east_antrim_council",
		"notes": "Some spaces are without addresses",
		"title": "Mid and East Antrim Council",
		"url": "https://www.midandeastantrim.gov.uk/resident/healthandwellbeing/a-safe-warm-well-come/"
	},
	"middlesbrough_council": {
		"count": 17,
		"data": [
			{ "keys": { "title": "name" }, "parse": "Address:<br>{{address}}<br>Opening times:{{hours}}", "type": "googlemap", "url": "https://www.google.com/maps/d/embed?mid=1UmvNYg24mUNr-rnBaiirspUi5LO8wXY&ehbc=2E312F&ll=54.55430542048388%2C-1.220620400000012&z=12" }
		],
		"geocount": 17,
		"id": "middlesbrough_council",
		"map": { "type": "googlemap", "url": "https://www.middlesbrough.gov.uk/community-support-and-safety/cost-living/warm-spaces" },
		"register": { "url": "mailto:livewellcentre@middlesbrough.gov.uk" },
		"title": "Middlesbrough Council",
		"url": "https://www.middlesbrough.gov.uk/community-support-and-safety/cost-living/warm-spaces"
	},
	"newham_council": {
		"count": 27,
		"data": [
			{ "keys": { "address": "{{ Address }}", "description": "Open to everyone: {{ Open_to_ev }}; Booking required: {{ Booking_ne }}; Toilets: {{ Toilets }}; Accessibility: {{ Accessibil }}; Baby changing: {{ Baby_chang }}; Warm drink: {{ Warm_drink }}; Warm food: {{ Warm_food_ }}; Device charging: {{ Device_cha }}; Use of computers: {{ Use of computers }}; Study space: {{ Study_spac }}; WiFi: {{ WiFi }}", "hours": "Opening_ti", "title": "Name", "url": "Website" }, "type": "arcgis", "url": "https://services1.arcgis.com/trOdpHvvP7HrTfdb/arcgis/rest/services/WarmHaven_2/FeatureServer/0/query?f=geojson&where=Operationa%20%3D%20%27Y%27&returnGeometry=true&spatialRel=esriSpatialRelIntersects&outFields=*&maxRecordCountFactor=4&outSR=4326&resultOffset=0&resultRecordCount=8000&cacheHint=true&quantizationParameters=%7B%22mode%22%3A%22view%22%2C%22originPosition%22%3A%22upperLeft%22%2C%22tolerance%22%3A1.0583333333333416%2C%22extent%22%3A%7B%22xmin%22%3A-492.28689999878407%2C%22ymin%22%3A6710410.039899997%2C%22xmax%22%3A7525.914900001139%2C%22ymax%22%3A6719613.525700003%2C%22spatialReference%22%3A%7B%22wkid%22%3A102100%2C%22latestWkid%22%3A3857%7D%7D%7D" }
		],
		"geocount": 27,
		"id": "newham_council",
		"map": { "type": "arcgis", "url": "https://lbnewham.maps.arcgis.com/apps/webappviewer/index.html?id=a6fb4671e35243698513effb08478e0d" },
		"title": "Newham Council",
		"url": "https://www.newham.gov.uk/warmhavens"
	},
	"norfolk_community_foundation": {
		"count": 134,
		"data": [
			{ "keys": { "address": "{{ Local Authority: Local Authority Name }}, {{ Area of Benefit Postcode }}", "title": "name" }, "type": "googlemap", "url": "https://www.google.com/maps/d/embed?mid=1WSlv1plWsNXZa9l3RJ_qtwkFYnFn8F0&ehbc=2E312F&ll=52.66981982723225%2C0.9787110000000077&z=8" }
		],
		"geocount": 130,
		"id": "norfolk_community_foundation",
		"map": { "type": "googlemap", "url": "https://www.google.com/maps/d/embed?mid=1WSlv1plWsNXZa9l3RJ_qtwkFYnFn8F0&ehbc=2E312F&ll=52.66981982723225%2C0.9787110000000077&z=8" },
		"title": "Norfolk Community Foundation",
		"url": "https://www.norfolkfoundation.com/hot-spots/"
	},
	"north_northamptonshire_council": {
		"count": 38,
		"data": [
			{ "type": "html", "url": "https://www.northnorthants.gov.uk/cost-living/warm-spaces" }
		],
		"geocount": 38,
		"id": "north_northamptonshire_council",
		"title": "North Northamptonshire Council",
		"url": "https://www.northnorthants.gov.uk/cost-living/warm-spaces"
	},
	"northumberland_county_council": {
		"count": 114,
		"data": [
			{ "keys": { "address": "B", "title": "A", "url": "C" }, "sheet": "sheet1", "startrow": "2", "type": "xls", "url": "https://www.northumberland.gov.uk/NorthumberlandCountyCouncil/media/Support/Warm%20Spaces/Warm-Spaces.xlsx" }
		],
		"geocount": 114,
		"id": "northumberland_county_council",
		"map": { "type": "tableau", "url": "https://www.northumberland.gov.uk/Support/Types-of-support/Warm-Spaces.aspx" },
		"register": { "url": "https://forms.office.com/pages/responsepage.aspx?id=3qkTu5CC8EKpgNw73-cPQETNnDx8cXJFhm1fWERtC3pUMUFDQ1RaU1pHMVpFV0w3RVM1UkZET1YyWi4u&fbclid=IwAR2aUhlf1MTPtvsKjP76MxNfwpmtpoWMkBPEjo6t_S2vseN6cYN4dfcTC7Q" },
		"title": "Northumberland County Council",
		"url": "https://www.northumberland.gov.uk/Support/Types-of-support/Warm-Spaces.aspx"
	},
	"oxford_council": {
		"count": 41,
		"data": [
			{ "keys": { "description": "description", "hours": "description", "title": "name" }, "type": "googlemap", "url": "https://www.google.com/maps/d/embed?mid=1Dsla6w3UdjubT3ZLY5UhZe3KGBNa2xg&ehbc=2E312F&ll=51.75012025595476%2C-1.2414510500000064&z=12" }
		],
		"geocount": 41,
		"id": "oxford_council",
		"map": { "type": "googlemap", "url": "https://www.google.com/maps/d/embed?mid=1Dsla6w3UdjubT3ZLY5UhZe3KGBNa2xg&ehbc=2E312F&ll=51.75012025595476%2C-1.2414510500000064&z=12" },
		"register": { "url": "mailto:lcooper@oxford.gov.uk" },
		"title": "Oxford Council",
		"url": "https://www.oxford.gov.uk/warmspaces"
	},
	"perth_and_kinross_council": {
		"count": 79,
		"data": [
			{ "keys": { "address": "Address", "contact": "Contact_De", "description": "Descriptio", "hours": "Descriptio", "title": "Name_of_Or" }, "type": "arcgis", "url": "https://services-eu1.arcgis.com/WD0cvOmDKf7CA0Xy/arcgis/rest/services/Warm_Spaces_in_Perth_and_Kinross/FeatureServer/5/query?f=geojson&cacheHint=true&maxRecordCountFactor=4&resultOffset=0&resultRecordCount=8000&where=1%3D1&outFields=Address,Contact_De,Descriptio,Name_of_Or,FID&orderByFields=FID&outSR=4326&spatialRel=esriSpatialRelIntersects" }
		],
		"geocount": 79,
		"id": "perth_and_kinross_council",
		"map": { "type": "arcgis", "url": "https://www.pkc.gov.uk/warmspaces" },
		"register": { "url": "mailto:CommunityPlanningPartnership@pkc.gov.uk" },
		"title": "Perth and Kinross Council",
		"url": "https://www.pkc.gov.uk/warmspaces"
	},
	"portsmouth_council": {
		"count": 35,
		"data": [
			{ "type": "html", "url": "https://www.portsmouth.gov.uk/services/benefits-and-support/cost-of-living-hub/warm-spaces/" }
		],
		"geocount": 27,
		"id": "portsmouth_council",
		"title": "Portsmouth Council",
		"url": "https://www.portsmouth.gov.uk/services/benefits-and-support/cost-of-living-hub/warm-spaces/"
	},
	"redcar_and_cleveland_council": {
		"count": 48,
		"data": [
			{ "type": "html", "url": "https://www.redcar-cleveland.gov.uk/cost-of-living-support/warm-spaces" }
		],
		"geocount": 48,
		"id": "redcar_and_cleveland_council",
		"map": { "type": "leaflet", "url": "https://www.redcar-cleveland.gov.uk/cost-of-living-support/warm-spaces" },
		"title": "Redcar and Cleveland Council",
		"url": "https://www.redcar-cleveland.gov.uk/cost-of-living-support/warm-spaces"
	},
	"richmond_upon_thames_council": {
		"count": 35,
		"data": [
			{ "type": "html", "url": "https://richmond.gov.uk/services/cost_of_living_hub/warm_spaces/warm_spaces_directory" }
		],
		"geocount": 35,
		"id": "richmond_upon_thames_council",
		"map": { "type": "leaflet", "url": "https://richmond.gov.uk/services/cost_of_living_hub/warm_spaces/warm_spaces_directory" },
		"title": "Richmond upon Thames Council",
		"url": "https://richmond.gov.uk/services/cost_of_living_hub/warm_spaces"
	},
	"rotherham_council": {
		"id": "rotherham_council",
		"notes": "Refers people to Warm Welcome",
		"title": "Rotherham Council",
		"url": "https://www.rotherham.gov.uk/warm-welcome"
	},
	"salisbury_council": {
		"id": "salisbury_council",
		"notes": "The list is a PDF",
		"title": "Salisbury Council",
		"url": "https://www.salisburycitycouncil.gov.uk/responsibilities/community-development/warm-and-welcoming-spaces"
	},
	"sandwell_council": {
		"count": 49,
		"data": [
			{ "type": "html", "url": "https://route2wellbeing.info/browse?source=bar&phrase=%23warmspaces" }
		],
		"geocount": 49,
		"id": "sandwell_council",
		"map": { "type": "googlemap", "url": "https://route2wellbeing.info/browse?source=bar&phrase=%23warmspaces" },
		"title": "Sandwell Council",
		"url": "https://www.sandwell.gov.uk/warmspaces"
	},
	"sefton_council": {
		"id": "sefton_council",
		"title": "Sefton Council",
		"url": "https://www.sefton.gov.uk/cost-of-living/warm-places-details/"
	},
	"sefton_cvs": {
		"count": 20,
		"data": [
			{ "keys": { "title": "name" }, "parse": "{{ hours }}", "type": "googlemap", "url": "https://www.google.com/maps/d/embed?mid=1ufQzUkVn58B6Hw1pTwvmGTYWtSE2DRA&ehbc=2E312F&ll=53.55888624022068%2C-3.004861084646202&z=11" }
		],
		"geocount": 20,
		"id": "sefton_cvs",
		"map": { "type": "googlemap", "url": "https://seftoncvs.org.uk/warmspaces/" },
		"title": "Sefton CVS",
		"url": "https://seftoncvs.org.uk/warmspaces/"
	},
	"sheffield_vas": {
		"count": 87,
		"data": [
			{ "keys": { "address": "address", "contact": "phonenumber", "description": "information", "hours": "openingtimes", "lat": "lat", "lon": "lng", "title": "name", "url": "website" }, "startrow": "2", "type": "csv", "url": "https://docs.google.com/spreadsheets/d/e/2PACX-1vQRbIq7B3EB_tSnW2Uoi4q1Sfrey5lxscOANLYHWYc5ZXDn5gD-5wXD3RCLSWJ2UehImGwEQn-rPss3/pub?output=csv" }
		],
		"geocount": 87,
		"id": "sheffield_vas",
		"map": { "type": "leaflet", "url": "https://foxdash.co.uk/vas/index.htm" },
		"title": "Sheffield VAS",
		"url": "https://www.vas.org.uk/sheffield-living-crisis-map-of-support/"
	},
	"southwalk_council": {
		"count": 32,
		"data": [
			{ "type": "html", "url": "https://www.southwark.gov.uk/benefits-and-support/cost-of-living-support/warm-spaces" }
		],
		"geocount": 32,
		"id": "southwalk_council",
		"title": "Southwalk Council",
		"url": "https://www.southwark.gov.uk/benefits-and-support/cost-of-living-support/warm-spaces"
	},
	"stafford_borough_council": {
		"count": 23,
		"data": [
			{ "type": "html", "url": "https://www.staffordbc.gov.uk/warm-spaces" }
		],
		"geocount": "0",
		"id": "stafford_borough_council",
		"register": "mailto:warmspaces@staffordbc.gov.uk",
		"title": "Stafford Borough Council",
		"url": "https://www.staffordbc.gov.uk/warm-spaces"
	},
	"stockport_council": {
		"count": 89,
		"data": [
			{ "keys": { "contact": "phone_number", "description": "facilities", "hours": "times", "title": "name", "url": "website" }, "type": "geojson", "url": "https://spatial.stockport.gov.uk/geoserver/wfs?service=WFS&version=1.1.0&request=GetFeature&typeName=neighbourhoods:warm_spaces2&outputFormat=application/json&bbox=-2.2731399536132817,53.320415173590504,-2.003288269042969,53.463729990468764,EPSG:4326&srsName=EPSG:4326" }
		],
		"geocount": 89,
		"id": "stockport_council",
		"map": { "type": "leaflet", "url": "https://www.stockport.gov.uk/warm-spaces" },
		"title": "Stockport Council",
		"url": "https://www.stockport.gov.uk/warm-spaces"
	},
	"stockton-on-tees_council": {
		"count": 62,
		"data": [
			{ "type": "html", "url": "https://www.stockton.gov.uk/warm-spaces" }
		],
		"geocount": 62,
		"id": "stockton-on-tees_council",
		"register": { "url": "https://www.stockton.gov.uk/warm-spaces-application" },
		"title": "Stockton-on-Tees Council",
		"url": "https://www.stockton.gov.uk/warm-spaces"
	},
	"stroud_cscic": {
		"count": 41,
		"data": [
			{ "type": "html", "url": "https://cscic.org/community-hubs/warm-spaces-in-stroud/" }
		],
		"geocount": 39,
		"id": "stroud_cscic",
		"title": "Stroud CSCIC",
		"url": "https://cscic.org/community-hubs/warm-spaces/"
	},
	"suffolk_-_rural_coffee_caravan": {
		"count": 223,
		"data": [
			{ "type": "html", "url": "https://ruralcoffeecaravan.org.uk/map/" }
		],
		"geocount": 223,
		"id": "suffolk_-_rural_coffee_caravan",
		"map": { "type": "googlemap", "url": "https://ruralcoffeecaravan.org.uk/map/" },
		"title": "Suffolk - Rural Coffee Caravan",
		"url": "https://ruralcoffeecaravan.org.uk/map/"
	},
	"sunderland_council": {
		"id": "sunderland_council",
		"map": { "type": "image", "url": "https://sunderland.gov.uk/image/27893/Cost-of-living-support-hub/large.jpg" },
		"title": "Sunderland Council",
		"url": "https://sunderland.gov.uk/article/24806/Warm-spaces?p=5"
	},
	"surrey_county_council_warm_hubs": {
		"count": 120,
		"data": [
			{ "keys": { "address": "Address", "hours": "OpenHours", "title": "Hub_Name" }, "licence": "none", "type": "geojson", "url": "https://services2.arcgis.com/lLe1XejBt1om9C8p/arcgis/rest/services/WarmHomes_v1/FeatureServer/0/query?f=geojson&where=1%3D1&returnGeometry=true&spatialRel=esriSpatialRelIntersects&outFields=*&maxRecordCountFactor=5&outSR=4326&resultOffset=0&resultRecordCount=5000&cacheHint=true&quantizationParameters=%7B%22mode%22%3A%22view%22%2C%22originPosition%22%3A%22upperLeft%22%2C%22tolerance%22%3A1.0583333333333336%2C%22extent%22%3A%7B%22xmin%22%3A483642.0031000003%2C%22ymin%22%3A132818.2544999998%2C%22xmax%22%3A540462.7911999999%2C%22ymax%22%3A171644.57689999975%2C%22spatialReference%22%3A%7B%22wkid%22%3A27700%2C%22latestWkid%22%3A27700%7D%7D%7D" }
		],
		"geocount": 120,
		"id": "surrey_county_council_warm_hubs",
		"map": { "type": "arcgis", "url": "https://surreycc.maps.arcgis.com/apps/webappviewer/index.html?id=e2f8a0a3debb427e8ce996cc8bd3f515" },
		"title": "Surrey County Council warm hubs",
		"url": "https://www.surreycc.gov.uk/health-and-welfare/support/welfare-support/everyday-living/warm-hubs"
	},
	"sutton_council": {
		"id": "sutton_council",
		"notes": "Refers to Warm Welcome UK",
		"title": "Sutton Council",
		"url": "https://www.sutton.gov.uk/-/warm-spaces-in-sutton"
	},
	"swansea_council": {
		"count": 41,
		"data": [
			{ "type": "html", "url": "https://www.swansea.gov.uk/swanseaspacescentral" },
			{ "type": "html", "url": "https://www.swansea.gov.uk/swanseaspaceseast" },
			{ "type": "html", "url": "https://www.swansea.gov.uk/swanseaspacesnorth" },
			{ "type": "html", "url": "https://www.swansea.gov.uk/swanseaspacesnorthwest" },
			{ "type": "html", "url": "https://www.swansea.gov.uk/swanseaspaceswest" },
			{ "type": "html", "url": "https://www.swansea.gov.uk/swanseaspacesgower" },
			{ "type": "googlemap2", "url": "https://www.google.com/maps/d/embed?mid=19SOxE0PBbR249as4UiDuQQVPOOArySw&ehbc=2E312F&ll=51.645226709090714%2C-4.029695849999997&z=11" }
		],
		"geocount": 27,
		"id": "swansea_council",
		"map": { "type": "googlemap", "url": "https://www.google.com/maps/d/embed?mid=19SOxE0PBbR249as4UiDuQQVPOOArySw&ehbc=2E312F&ll=51.645226709090714%2C-4.029695849999997&z=11" },
		"title": "Swansea Council",
		"url": "https://www.swansea.gov.uk/swanseaspaces"
	},
	"tewkesbury_council": {
		"id": "tewkesbury_council",
		"register": { "url": "https://www.tewkesbury.gov.uk/forms/warm-spaces-directory-registration" },
		"title": "Tewkesbury Council",
		"url": "https://www.tewkesbury.gov.uk/warm-spaces"
	},
	"torbay_council": {
		"count": 37,
		"data": [
			{ "type": "html", "url": "https://www.torbay.gov.uk/benefits/cost-of-living/warm-spaces/find-a-warm-space/" }
		],
		"geocount": 37,
		"id": "torbay_council",
		"map": { "type": "googlemap", "url": "https://www.torbay.gov.uk/benefits/cost-of-living/warm-spaces/find-a-warm-space/" },
		"title": "Torbay Council",
		"url": "https://www.torbay.gov.uk/benefits/cost-of-living/warm-spaces/"
	},
	"wakefield_council": {
		"count": "0",
		"data": [
			{ "robots": "", "type": "html", "url": "https://www.wakefield.gov.uk/more-money-in-my-pocket/warm-spaces" }
		],
		"geocount": "0",
		"id": "wakefield_council",
		"notes": "Wakefield Council website blocks automatic access of webpages",
		"title": "Wakefield Council",
		"url": "https://www.wakefield.gov.uk/more-money-in-my-pocket/warm-spaces"
	},
	"wandsworth_council": {
		"count": 36,
		"data": [
			{ "type": "html", "url": "https://www.wandsworth.gov.uk/cost-of-living-hub/warm-spaces/warm-spaces-directory/" }
		],
		"geocount": 36,
		"id": "wandsworth_council",
		"map": { "type": "leaflet", "url": "https://www.wandsworth.gov.uk/cost-of-living-hub/warm-spaces/warm-spaces-directory/" },
		"register": { "url": "https://wandsworth-self.achieveservice.com/service/register_interest_in_joining_the_warm_spaces_network" },
		"title": "Wandsworth Council",
		"url": "https://www.wandsworth.gov.uk/warm-spaces"
	},
	"warm_spaces": {
		"count": 1186,
		"data": [
			{ "type": "squarespace", "url": "https://warmspaces.org/locations/" }
		],
		"geocount": 1186,
		"id": "warm_spaces",
		"map": { "type": "googlemap", "url": "https://warmspaces.org/spaces" },
		"register": { "url": "https://docs.google.com/forms/d/e/1FAIpQLSeQgc1ROLZKKO3KjnfzR_N2OH8mfWPhjkVkT5Xz4cEFj-k72Q/viewform" },
		"title": "Warm spaces",
		"url": "https://warmspaces.org/"
	},
	"warm_welcome": {
		"count": 3320,
		"data": [
			{ "keys": { "address": "streetaddress", "lat": "loc_lat", "lon": "loc_long", "title": "name" }, "licence": "none", "type": "storepoint", "url": "https://api.storepoint.co/v1/16320a694c8cc5/locations?rq" }
		],
		"geocount": 3320,
		"id": "warm_welcome",
		"map": { "type": "mapbox", "url": "https://www.warmwelcome.uk/#find-a-space" },
		"register": { "url": "https://www.warmwelcome.uk/get-started/signup" },
		"title": "Warm Welcome",
		"url": "https://www.warmwelcome.uk/"
	},
	"west_northamptonshire": {
		"count": 64,
		"data": [
			{ "type": "html", "url": "https://www.westnorthants.gov.uk/cost-living-support/looking-warm-spaces" }
		],
		"geocount": 62,
		"id": "west_northamptonshire",
		"map": { "type": "googlemap", "url": "https://www.google.com/maps/d/viewer?hl=en&mid=1BtrOICbcVc3tUsrS_DLsfSHuLkqctWA&ll=52.228250747031765%2C-1.0235380000000172&z=10" },
		"register": { "url": "https://forms.office.com/r/EHJpfj9uCF" },
		"title": "West Northamptonshire",
		"url": "https://www.westnorthants.gov.uk/cost-living-support/looking-warm-spaces"
	},
	"westminster_council": {
		"datatemp": [
			{ "keys": { "address": "Address", "description": "Extra_Info", "title": "Institution", "url": "Link" }, "type": "arcgis", "url": "https://utility.arcgis.com/usrsvcs/servers/547b97991ccc41e3a7953c069d982a0e/rest/services/WCC/AGOL/MapServer/224/query?f=json&where=Category%20%3D%20%27Cultural%20%27&returnGeometry=true&spatialRel=esriSpatialRelIntersects&geometry=%7B%22xmin%22%3A-24460%2C%22ymin%22%3A6706890%2C%22xmax%22%3A-9784%2C%22ymax%22%3A6716675%2C%22spatialReference%22%3A%7B%22wkid%22%3A102100%7D%7D&geometryType=esriGeometryEnvelope&inSR=102100&outFields=*&outSR=102100&quantizationParameters=%7B%22mode%22%3A%22view%22%2C%22originPosition%22%3A%22upperLeft%22%2C%22tolerance%22%3A9.554628535634157%2C%22extent%22%3A%7B%22xmin%22%3A-24460%2C%22ymin%22%3A6706890%2C%22xmax%22%3A-9784%2C%22ymax%22%3A6716675%2C%22spatialReference%22%3A%7B%22wkid%22%3A27700%2C%22latestWkid%22%3A27700%7D%7D%7D" }
		],
		"id": "westminster_council",
		"map": { "type": "arcgis", "url": "https://lbhf.maps.arcgis.com/apps/webappviewer/index.html?id=8bf1f9ed1a474940b0f92e710e3f0379" },
		"title": "Westminster Council",
		"url": "https://www.westminster.gov.uk/winter-in-the-city"
	},
	"wigan_council": {
		"count": 74,
		"data": [
			{ "keys": { "title": "name" }, "parse": "Address: {{ address }}<br>Opening Hours for Warm Hub: {{ hours }}<br>Website: {{ url }}<br>.*", "type": "googlemap", "url": "https://www.google.com/maps/d/embed?mid=1zBuimD6bspFrz6sKCs9DgA-cE4BbM3Y&ll=53.52978513678878%2C-2.5874970965000044&z=11" }
		],
		"geocount": 74,
		"id": "wigan_council",
		"map": { "type": "googlemap", "url": "https://www.google.com/maps/d/embed?mid=1zBuimD6bspFrz6sKCs9DgA-cE4BbM3Y" },
		"title": "Wigan Council",
		"url": "https://www.wigan.gov.uk/Council/The-Deal/Deal-Communities/Here-for-you/Warm-welcoming-spaces.aspx"
	},
	"wokingham_council": {
		"id": "wokingham_council",
		"register": { "url": "https://www.wokingham.gov.uk/cost-of-living/run-a-warm-space/" },
		"title": "Wokingham Council",
		"url": "https://www.wokingham.gov.uk/cost-of-living/warm-spaces/"
	},
	"wolverhampton_council": {
		"count": 24,
		"data": [
			{ "type": "html", "url": "https://www.wolverhampton.gov.uk/community/cost-of-living-support/warm-spaces" }
		],
		"geocount": 21,
		"id": "wolverhampton_council",
		"title": "Wolverhampton Council",
		"url": "https://www.wolverhampton.gov.uk/community/cost-of-living-support/warm-spaces"
	}
}
